[
  {
    "p": "A Midsummer nights dream",
    "l": "3.1.1",
    "s": "BOTTOM",
    "t": "Are we all met?"
  },
  {
    "p": "A Midsummer nights dream",
    "l": "3.1.2",
    "s": "QUINCE",
    "t": "Pat, pat; and heres a marvellous convenient place\n\nfor our rehearsal. This green plot shall be our\n\nstage, this hawthorn-brake our tiring-house; and we\n\nwill do it in action as we will do it before the duke."
  },
  {
    "p": "A Midsummer nights dream",
    "l": "3.1.6",
    "s": "BOTTOM",
    "t": "Peter Quince,--"
  },
  {
    "p": "A Midsummer nights dream",
    "l": "3.1.7",
    "s": "QUINCE",
    "t": "What sayest thou, bully Bottom?"
  },
  {
    "p": "A Midsummer nights dream",
    "l": "3.1.8",
    "s": "BOTTOM",
    "t": "There are things in this comedy of Pyramus and\n\nThisby that will never please. First, Pyramus must\n\ndraw a sword to kill himself; which the ladies\n\ncannot abide. How answer you that?"
  },
  {
    "p": "A Midsummer nights dream",
    "l": "3.1.12",
    "s": "SNOUT",
    "t": "Byr lakin, a parlous fear."
  },
  {
    "p": "A Midsummer nights dream",
    "l": "3.1.13",
    "s": "STARVELING",
    "t": "I believe we must leave the killing out, when all is done."
  },
  {
    "p": "A Midsummer nights dream",
    "l": "3.1.14",
    "s": "BOTTOM",
    "t": "Not a whit: I have a device to make all well.\n\nWrite me a prologue; and let the prologue seem to\n\nsay, we will do no harm with our swords, and that\n\nPyramus is not killed indeed; and, for the more\n\nbetter assurance, tell them that I, Pyramus, am not\n\nPyramus, but Bottom the weaver: this will put them\n\nout of fear."
  },
  {
    "p": "A Midsummer nights dream",
    "l": "3.1.21",
    "s": "QUINCE",
    "t": "Well, we will have such a prologue; and it shall be\n\nwritten in eight and six."
  },
  {
    "p": "A Midsummer nights dream",
    "l": "3.1.23",
    "s": "BOTTOM",
    "t": "No, make it two more; let it be written in eight and eight."
  },
  {
    "p": "A Midsummer nights dream",
    "l": "3.1.24",
    "s": "SNOUT",
    "t": "Will not the ladies be afeard of the lion?"
  },
  {
    "p": "A Midsummer nights dream",
    "l": "3.1.25",
    "s": "STARVELING",
    "t": "I fear it, I promise you."
  },
  {
    "p": "A Midsummer nights dream",
    "l": "3.1.26",
    "s": "BOTTOM",
    "t": "Masters, you ought to consider with yourselves: to\n\nbring in--God shield us!--a lion among ladies, is a\n\nmost dreadful thing; for there is not a more fearful\n\nwild-fowl than your lion living; and we ought to\n\nlook to t."
  },
  {
    "p": "A Midsummer nights dream",
    "l": "3.1.31",
    "s": "SNOUT",
    "t": "Therefore another prologue must tell he is not a lion."
  },
  {
    "p": "A Midsummer nights dream",
    "l": "3.1.32",
    "s": "BOTTOM",
    "t": "Nay, you must name his name, and half his face must\n\nbe seen through the lions neck: and he himself\n\nmust speak through, saying thus, or to the same\n\ndefect,--Ladies,--or Fair-ladies--I would wish\n\nYou,--or I would request you,--or I would\n\nentreat you,--not to fear, not to tremble: my life\n\nfor yours. If you think I come hither as a lion, it\n\nwere pity of my life: no I am no such thing; I am a\n\nman as other men are; and there indeed let him name\n\nhis name, and tell them plainly he is Snug the joiner."
  },
  {
    "p": "A Midsummer nights dream",
    "l": "3.1.42",
    "s": "QUINCE",
    "t": "Well it shall be so. But there is two hard things;\n\nthat is, to bring the moonlight into a chamber; for,\n\nyou know, Pyramus and Thisby meet by moonlight."
  },
  {
    "p": "A Midsummer nights dream",
    "l": "3.1.45",
    "s": "SNOUT",
    "t": "Doth the moon shine that night we play our play?"
  },
  {
    "p": "A Midsummer nights dream",
    "l": "3.1.46",
    "s": "BOTTOM",
    "t": "A calendar, a calendar! look in the almanac; find\n\nout moonshine, find out moonshine."
  },
  {
    "p": "A Midsummer nights dream",
    "l": "3.1.48",
    "s": "QUINCE",
    "t": "Yes, it doth shine that night."
  },
  {
    "p": "A Midsummer nights dream",
    "l": "3.1.49",
    "s": "BOTTOM",
    "t": "Why, then may you leave a casement of the great\n\nchamber window, where we play, open, and the moon\n\nmay shine in at the casement."
  },
  {
    "p": "A Midsummer nights dream",
    "l": "3.1.52",
    "s": "QUINCE",
    "t": "Ay; or else one must come in with a bush of thorns\n\nand a lanthorn, and say he comes to disfigure, or to\n\npresent, the person of Moonshine. Then, there is\n\nanother thing: we must have a wall in the great\n\nchamber; for Pyramus and Thisby says the story, did\n\ntalk through the chink of a wall."
  },
  {
    "p": "A Midsummer nights dream",
    "l": "3.1.58",
    "s": "SNOUT",
    "t": "You can never bring in a wall. What say you, Bottom?"
  },
  {
    "p": "A Midsummer nights dream",
    "l": "3.1.59",
    "s": "BOTTOM",
    "t": "Some man or other must present Wall: and let him\n\nhave some plaster, or some loam, or some rough-cast\n\nabout him, to signify wall; and let him hold his\n\nfingers thus, and through that cranny shall Pyramus\n\nand Thisby whisper."
  },
  {
    "p": "A Midsummer nights dream",
    "l": "3.1.64",
    "s": "QUINCE",
    "t": "If that may be, then all is well. Come, sit  down,\n\nevery mothers son, and rehearse your parts.\n\nPyramus, you begin: when you have spoken your\n\nspeech, enter into that brake: and so every one\n\naccording to his cue."
  },
  {
    "p": "A Midsummer nights dream",
    "l": "3.1.69",
    "s": "PUCK",
    "t": "What hempen home-spuns have we swaggering here,\n\nSo near the cradle of the fairy queen?\n\nWhat, a play toward! Ill be an auditor;\n\nAn actor too, perhaps, if I see cause."
  },
  {
    "p": "A Midsummer nights dream",
    "l": "3.1.73",
    "s": "QUINCE",
    "t": "Speak, Pyramus. Thisby, stand forth."
  },
  {
    "p": "A Midsummer nights dream",
    "l": "3.1.74",
    "s": "BOTTOM",
    "t": "Thisby, the flowers of odious savours sweet,--"
  },
  {
    "p": "A Midsummer nights dream",
    "l": "3.1.75",
    "s": "QUINCE",
    "t": "Odours, odours."
  },
  {
    "p": "A Midsummer nights dream",
    "l": "3.1.76",
    "s": "BOTTOM",
    "t": "--odours savours sweet:\n\nSo hath thy breath, my dearest Thisby dear.\n\nBut hark, a voice! stay thou but here awhile,\n\nAnd by and by I will to thee appear."
  },
  {
    "p": "A Midsummer nights dream",
    "l": "3.1.80",
    "s": "PUCK",
    "t": "A stranger Pyramus than eer played here."
  },
  {
    "p": "A Midsummer nights dream",
    "l": "3.1.81",
    "s": "FLUTE",
    "t": "Must I speak now?"
  },
  {
    "p": "A Midsummer nights dream",
    "l": "3.1.82",
    "s": "QUINCE",
    "t": "Ay, marry, must you; for you must understand he goes\n\nbut to see a noise that he heard, and is to come again."
  },
  {
    "p": "A Midsummer nights dream",
    "l": "3.1.84",
    "s": "FLUTE",
    "t": "Most radiant Pyramus, most lily-white of hue,\n\nOf colour like the red rose on triumphant brier,\n\nMost brisky juvenal and eke most lovely Jew,\n\nAs true as truest horse that yet would never tire,\n\nIll meet thee, Pyramus, at Ninnys tomb."
  },
  {
    "p": "A Midsummer nights dream",
    "l": "3.1.89",
    "s": "QUINCE",
    "t": "Ninus tomb, man: why, you must not speak that\n\nyet; that you answer to Pyramus: you speak all your\n\npart at once, cues and all Pyramus enter: your cue\n\nis past; it is, never tire."
  },
  {
    "p": "A Midsummer nights dream",
    "l": "3.1.93",
    "s": "FLUTE",
    "t": "O,--As true as truest horse, that yet would\n\nnever tire."
  },
  {
    "p": "A Midsummer nights dream",
    "l": "3.1.95",
    "s": "BOTTOM",
    "t": "If I were fair, Thisby, I were only thine."
  },
  {
    "p": "A Midsummer nights dream",
    "l": "3.1.96",
    "s": "QUINCE",
    "t": "O monstrous! O strange! we are haunted. Pray,\n\nmasters! fly, masters! Help!"
  },
  {
    "p": "A Midsummer nights dream",
    "l": "3.1.98",
    "s": "PUCK",
    "t": "Ill follow you, Ill lead you about a round,\n\nThrough bog, through bush, through brake, through brier:\n\nSometime a horse Ill be, sometime a hound,\n\nA hog, a headless bear, sometime a fire;\n\nAnd neigh, and bark, and grunt, and roar, and burn,\n\nLike horse, hound, hog, bear, fire, at every turn."
  },
  {
    "p": "A Midsummer nights dream",
    "l": "3.1.104",
    "s": "BOTTOM",
    "t": "Why do they run away? this is a knavery of them to\n\nmake me afeard."
  },
  {
    "p": "A Midsummer nights dream",
    "l": "3.1.106",
    "s": "SNOUT",
    "t": "O Bottom, thou art changed! what do I see on thee?"
  },
  {
    "p": "A Midsummer nights dream",
    "l": "3.1.107",
    "s": "BOTTOM",
    "t": "What do you see? you see an asshead of your own, do\n\nyou?"
  },
  {
    "p": "A Midsummer nights dream",
    "l": "3.1.109",
    "s": "QUINCE",
    "t": "Bless thee, Bottom! bless thee! thou art\n\ntranslated."
  },
  {
    "p": "A Midsummer nights dream",
    "l": "3.1.111",
    "s": "BOTTOM",
    "t": "I see their knavery: this is to make an ass of me;\n\nto fright me, if they could. But I will not stir\n\nfrom this place, do what they can: I will walk up\n\nand down here, and I will sing, that they shall hear\n\nI am not afraid.\n\nThe ousel cock so black of hue,\n\nWith orange-tawny bill,\n\nThe throstle with his note so true,\n\nThe wren with little quill,--"
  },
  {
    "p": "A Midsummer nights dream",
    "l": "3.1.120",
    "s": "TITANIA",
    "t": "[Awaking]  What angel wakes me from my flowery bed?"
  },
  {
    "p": "A Midsummer nights dream",
    "l": "3.1.121",
    "s": "BOTTOM",
    "t": "[Sings]\n\nThe finch, the sparrow and the lark,\n\nThe plain-song cuckoo gray,\n\nWhose note full many a man doth mark,\n\nAnd dares not answer nay;--\n\nfor, indeed, who would set his wit to so foolish\n\na bird? who would give a bird the lie, though he cry\n\ncuckoo never so?"
  },
  {
    "p": "A Midsummer nights dream",
    "l": "3.1.129",
    "s": "TITANIA",
    "t": "I pray thee, gentle mortal, sing again:\n\nMine ear is much enamourd of thy note;\n\nSo is mine eye enthralled to thy shape;\n\nAnd thy fair virtues force perforce doth move me\n\nOn the first view to say, to swear, I love thee."
  },
  {
    "p": "A Midsummer nights dream",
    "l": "3.1.134",
    "s": "BOTTOM",
    "t": "Methinks, mistress, you should have little reason\n\nfor that: and yet, to say the truth, reason and\n\nlove keep little company together now-a-days; the\n\nmore the pity that some honest neighbours will not\n\nmake them friends. Nay, I can gleek upon occasion."
  },
  {
    "p": "A Midsummer nights dream",
    "l": "3.1.139",
    "s": "TITANIA",
    "t": "Thou art as wise as thou art beautiful."
  },
  {
    "p": "A Midsummer nights dream",
    "l": "3.1.140",
    "s": "BOTTOM",
    "t": "Not so, neither: but if I had wit enough to get out\n\nof this wood, I have enough to serve mine own turn."
  },
  {
    "p": "A Midsummer nights dream",
    "l": "3.1.142",
    "s": "TITANIA",
    "t": "Out of this wood do not desire to go:\n\nThou shalt remain here, whether thou wilt or no.\n\nI am a spirit of no common rate;\n\nThe summer still doth tend upon my state;\n\nAnd I do love thee: therefore, go with me;\n\nIll give thee fairies to attend on thee,\n\nAnd they shall fetch thee jewels from the deep,\n\nAnd sing while thou on pressed flowers dost sleep;\n\nAnd I will purge thy mortal grossness so\n\nThat thou shalt like an airy spirit go.\n\nPeaseblossom! Cobweb! Moth! and Mustardseed!"
  },
  {
    "p": "A Midsummer nights dream",
    "l": "3.1.153",
    "s": "PEASEBLOSSOM",
    "t": "Ready."
  },
  {
    "p": "A Midsummer nights dream",
    "l": "3.1.154",
    "s": "COBWEB",
    "t": "And I."
  },
  {
    "p": "A Midsummer nights dream",
    "l": "3.1.155",
    "s": "MOTH",
    "t": "And I."
  },
  {
    "p": "A Midsummer nights dream",
    "l": "3.1.156",
    "s": "MUSTARDSEED",
    "t": "And I."
  },
  {
    "p": "A Midsummer nights dream",
    "l": "3.1.157",
    "s": "ALL",
    "t": "Where shall we go?"
  },
  {
    "p": "A Midsummer nights dream",
    "l": "3.1.158",
    "s": "TITANIA",
    "t": "Be kind and courteous to this gentleman;\n\nHop in his walks and gambol in his eyes;\n\nFeed him with apricocks and dewberries,\n\nWith purple grapes, green figs, and mulberries;\n\nThe honey-bags steal from the humble-bees,\n\nAnd for night-tapers crop their waxen thighs\n\nAnd light them at the fiery glow-worms eyes,\n\nTo have my love to bed and to arise;\n\nAnd pluck the wings from Painted butterflies\n\nTo fan the moonbeams from his sleeping eyes:\n\nNod to him, elves, and do him courtesies."
  },
  {
    "p": "A Midsummer nights dream",
    "l": "3.1.169",
    "s": "PEASEBLOSSOM",
    "t": "Hail, mortal!"
  },
  {
    "p": "A Midsummer nights dream",
    "l": "3.1.170",
    "s": "COBWEB",
    "t": "Hail!"
  },
  {
    "p": "A Midsummer nights dream",
    "l": "3.1.171",
    "s": "MOTH",
    "t": "Hail!"
  },
  {
    "p": "A Midsummer nights dream",
    "l": "3.1.172",
    "s": "MUSTARDSEED",
    "t": "Hail!"
  },
  {
    "p": "A Midsummer nights dream",
    "l": "3.1.173",
    "s": "BOTTOM",
    "t": "I cry your worships mercy, heartily: I beseech your\n\nworships name."
  },
  {
    "p": "A Midsummer nights dream",
    "l": "3.1.175",
    "s": "COBWEB",
    "t": "Cobweb."
  },
  {
    "p": "A Midsummer nights dream",
    "l": "3.1.176",
    "s": "BOTTOM",
    "t": "I shall desire you of more acquaintance, good Master\n\nCobweb: if I cut my finger, I shall make bold with\n\nyou. Your name, honest gentleman?"
  },
  {
    "p": "A Midsummer nights dream",
    "l": "3.1.179",
    "s": "PEASEBLOSSOM",
    "t": "Peaseblossom."
  },
  {
    "p": "A Midsummer nights dream",
    "l": "3.1.180",
    "s": "BOTTOM",
    "t": "I pray you, commend me to Mistress Squash, your\n\nmother, and to Master Peascod, your father. Good\n\nMaster Peaseblossom, I shall desire you of more\n\nacquaintance too. Your name, I beseech you, sir?"
  },
  {
    "p": "A Midsummer nights dream",
    "l": "3.1.184",
    "s": "MUSTARDSEED",
    "t": "Mustardseed."
  },
  {
    "p": "A Midsummer nights dream",
    "l": "3.1.185",
    "s": "BOTTOM",
    "t": "Good Master Mustardseed, I know your patience well:\n\nthat same cowardly, giant-like ox-beef hath\n\ndevoured many a gentleman of your house: I promise\n\nyou your kindred had made my eyes water ere now. I\n\ndesire your more acquaintance, good Master\n\nMustardseed."
  },
  {
    "p": "A Midsummer nights dream",
    "l": "3.1.191",
    "s": "TITANIA",
    "t": "Come, wait upon him; lead him to my bower.\n\nThe moon methinks looks with a watery eye;\n\nAnd when she weeps, weeps every little flower,\n\nLamenting some enforced chastity.\n\nTie up my loves tongue bring him silently."
  },
  {
    "p": "A Midsummer nights dream",
    "l": "3.2.1",
    "s": "OBERON",
    "t": "I wonder if Titania be awaked;\n\nThen, what it was that next came in her eye,\n\nWhich she must dote on in extremity.\n\nHere comes my messenger.\n\nHow now, mad spirit!\n\nWhat night-rule now about this haunted grove?"
  },
  {
    "p": "A Midsummer nights dream",
    "l": "3.2.7",
    "s": "PUCK",
    "t": "My mistress with a monster is in love.\n\nNear to her close and consecrated bower,\n\nWhile she was in her dull and sleeping hour,\n\nA crew of patches, rude mechanicals,\n\nThat work for bread upon Athenian stalls,\n\nWere met together to rehearse a play\n\nIntended for great Theseus nuptial-day.\n\nThe shallowest thick-skin of that barren sort,\n\nWho Pyramus presented, in their sport\n\nForsook his scene and enterd in a brake\n\nWhen I did him at this advantage take,\n\nAn asss nole I fixed on his head:\n\nAnon his Thisbe must be answered,\n\nAnd forth my mimic comes. When they him spy,\n\nAs wild geese that the creeping fowler eye,\n\nOr russet-pated choughs, many in sort,\n\nRising and cawing at the guns report,\n\nSever themselves and madly sweep the sky,\n\nSo, at his sight, away his fellows fly;\n\nAnd, at our stamp, here oer and oer one falls;\n\nHe murder cries and help from Athens calls.\n\nTheir sense thus weak, lost with their fears\n\nthus strong,\n\nMade senseless things begin to do them wrong;\n\nFor briers and thorns at their apparel snatch;\n\nSome sleeves, some hats, from yielders all\n\nthings catch.\n\nI led them on in this distracted fear,\n\nAnd left sweet Pyramus translated there:\n\nWhen in that moment, so it came to pass,\n\nTitania waked and straightway loved an ass."
  },
  {
    "p": "A Midsummer nights dream",
    "l": "3.2.38",
    "s": "OBERON",
    "t": "This falls out better than I could devise.\n\nBut hast thou yet latchd the Athenians eyes\n\nWith the love-juice, as I did bid thee do?"
  },
  {
    "p": "A Midsummer nights dream",
    "l": "3.2.41",
    "s": "PUCK",
    "t": "I took him sleeping,--that is finishd too,--\n\nAnd the Athenian woman by his side:\n\nThat, when he waked, of force she must be eyed."
  },
  {
    "p": "A Midsummer nights dream",
    "l": "3.2.44",
    "s": "OBERON",
    "t": "Stand close: this is the same Athenian."
  },
  {
    "p": "A Midsummer nights dream",
    "l": "3.2.45",
    "s": "PUCK",
    "t": "This is the woman, but not this the man."
  },
  {
    "p": "A Midsummer nights dream",
    "l": "3.2.46",
    "s": "DEMETRIUS",
    "t": "O, why rebuke you him that loves you so?\n\nLay breath so bitter on your bitter foe."
  },
  {
    "p": "A Midsummer nights dream",
    "l": "3.2.48",
    "s": "HERMIA",
    "t": "Now I but chide; but I should use thee worse,\n\nFor thou, I fear, hast given me cause to curse,\n\nIf thou hast slain Lysander in his sleep,\n\nBeing oer shoes in blood, plunge in the deep,\n\nAnd kill me too.\n\nThe sun was not so true unto the day\n\nAs he to me: would he have stolen away\n\nFrom sleeping Hermia? Ill believe as soon\n\nThis whole earth may be bored and that the moon\n\nMay through the centre creep and so displease\n\nHer brothers noontide with Antipodes.\n\nIt cannot be but thou hast murderd him;\n\nSo should a murderer look, so dead, so grim."
  },
  {
    "p": "A Midsummer nights dream",
    "l": "3.2.61",
    "s": "DEMETRIUS",
    "t": "So should the murderd look, and so should I,\n\nPierced through the heart with your stern cruelty:\n\nYet you, the murderer, look as bright, as clear,\n\nAs yonder Venus in her glimmering sphere."
  },
  {
    "p": "A Midsummer nights dream",
    "l": "3.2.65",
    "s": "HERMIA",
    "t": "Whats this to my Lysander? where is he?\n\nAh, good Demetrius, wilt thou give him me?"
  },
  {
    "p": "A Midsummer nights dream",
    "l": "3.2.67",
    "s": "DEMETRIUS",
    "t": "I had rather give his carcass to my hounds."
  },
  {
    "p": "A Midsummer nights dream",
    "l": "3.2.68",
    "s": "HERMIA",
    "t": "Out, dog! out, cur! thou drivest me past the bounds\n\nOf maidens patience. Hast thou slain him, then?\n\nHenceforth be never numberd among men!\n\nO, once tell true, tell true, even for my sake!\n\nDurst thou have lookd upon him being awake,\n\nAnd hast thou killd him sleeping? O brave touch!\n\nCould not a worm, an adder, do so much?\n\nAn adder did it; for with doubler tongue\n\nThan thine, thou serpent, never adder stung."
  },
  {
    "p": "A Midsummer nights dream",
    "l": "3.2.77",
    "s": "DEMETRIUS",
    "t": "You spend your passion on a misprised mood:\n\nI am not guilty of Lysanders blood;\n\nNor is he dead, for aught that I can tell."
  },
  {
    "p": "A Midsummer nights dream",
    "l": "3.2.80",
    "s": "HERMIA",
    "t": "I pray thee, tell me then that he is well."
  },
  {
    "p": "A Midsummer nights dream",
    "l": "3.2.81",
    "s": "DEMETRIUS",
    "t": "An if I could, what should I get therefore?"
  },
  {
    "p": "A Midsummer nights dream",
    "l": "3.2.82",
    "s": "HERMIA",
    "t": "A privilege never to see me more.\n\nAnd from thy hated presence part I so:\n\nSee me no more, whether he be dead or no."
  },
  {
    "p": "A Midsummer nights dream",
    "l": "3.2.85",
    "s": "DEMETRIUS",
    "t": "There is no following her in this fierce vein:\n\nHere therefore for a while I will remain.\n\nSo sorrows heaviness doth heavier grow\n\nFor debt that bankrupt sleep doth sorrow owe:\n\nWhich now in some slight measure it will pay,\n\nIf for his tender here I make some stay."
  },
  {
    "p": "A Midsummer nights dream",
    "l": "3.2.91",
    "s": "OBERON",
    "t": "What hast thou done? thou hast mistaken quite\n\nAnd laid the love-juice on some true-loves sight:\n\nOf thy misprision must perforce ensue\n\nSome true love turnd and not a false turnd true."
  },
  {
    "p": "A Midsummer nights dream",
    "l": "3.2.95",
    "s": "PUCK",
    "t": "Then fate oer-rules, that, one man holding troth,\n\nA million fail, confounding oath on oath."
  },
  {
    "p": "A Midsummer nights dream",
    "l": "3.2.97",
    "s": "OBERON",
    "t": "About the wood go swifter than the wind,\n\nAnd Helena of Athens look thou find:\n\nAll fancy-sick she is and pale of cheer,\n\nWith sighs of love, that costs the fresh blood dear:\n\nBy some illusion see thou bring her here:\n\nIll charm his eyes against she do appear."
  },
  {
    "p": "A Midsummer nights dream",
    "l": "3.2.103",
    "s": "PUCK",
    "t": "I go, I go; look how I go,\n\nSwifter than arrow from the Tartars bow."
  },
  {
    "p": "A Midsummer nights dream",
    "l": "3.2.105",
    "s": "OBERON",
    "t": "Flower of this purple dye,\n\nHit with Cupids archery,\n\nSink in apple of his eye.\n\nWhen his love he doth espy,\n\nLet her shine as gloriously\n\nAs the Venus of the sky.\n\nWhen thou wakest, if she be by,\n\nBeg of her for remedy."
  },
  {
    "p": "A Midsummer nights dream",
    "l": "3.2.113",
    "s": "PUCK",
    "t": "Captain of our fairy band,\n\nHelena is here at hand;\n\nAnd the youth, mistook by me,\n\nPleading for a lovers fee.\n\nShall we their fond pageant see?\n\nLord, what fools these mortals be!"
  },
  {
    "p": "A Midsummer nights dream",
    "l": "3.2.119",
    "s": "OBERON",
    "t": "Stand aside: the noise they make\n\nWill cause Demetrius to awake."
  },
  {
    "p": "A Midsummer nights dream",
    "l": "3.2.121",
    "s": "PUCK",
    "t": "Then will two at once woo one;\n\nThat must needs be sport alone;\n\nAnd those things do best please me\n\nThat befal preposterously."
  },
  {
    "p": "A Midsummer nights dream",
    "l": "3.2.125",
    "s": "LYSANDER",
    "t": "Why should you think that I should woo in scorn?\n\nScorn and derision never come in tears:\n\nLook, when I vow, I weep; and vows so born,\n\nIn their nativity all truth appears.\n\nHow can these things in me seem scorn to you,\n\nBearing the badge of faith, to prove them true?"
  },
  {
    "p": "A Midsummer nights dream",
    "l": "3.2.131",
    "s": "HELENA",
    "t": "You do advance your cunning more and more.\n\nWhen truth kills truth, O devilish-holy fray!\n\nThese vows are Hermias: will you give her oer?\n\nWeigh oath with oath, and you will nothing weigh:\n\nYour vows to her and me, put in two scales,\n\nWill even weigh, and both as light as tales."
  },
  {
    "p": "A Midsummer nights dream",
    "l": "3.2.137",
    "s": "LYSANDER",
    "t": "I had no judgment when to her I swore."
  },
  {
    "p": "A Midsummer nights dream",
    "l": "3.2.138",
    "s": "HELENA",
    "t": "Nor none, in my mind, now you give her oer."
  },
  {
    "p": "A Midsummer nights dream",
    "l": "3.2.139",
    "s": "LYSANDER",
    "t": "Demetrius loves her, and he loves not you."
  },
  {
    "p": "A Midsummer nights dream",
    "l": "3.2.140",
    "s": "DEMETRIUS",
    "t": "[Awaking]  O Helena, goddess, nymph, perfect, divine!\n\nTo what, my love, shall I compare thine eyne?\n\nCrystal is muddy. O, how ripe in show\n\nThy lips, those kissing cherries, tempting grow!\n\nThat pure congealed white, high Taurus snow,\n\nFannd with the eastern wind, turns to a crow\n\nWhen thou holdst up thy hand: O, let me kiss\n\nThis princess of pure white, this seal of bliss!"
  },
  {
    "p": "A Midsummer nights dream",
    "l": "3.2.148",
    "s": "HELENA",
    "t": "O spite! O hell! I see you all are bent\n\nTo set against me for your merriment:\n\nIf you we re civil and knew courtesy,\n\nYou would not do me thus much injury.\n\nCan you not hate me, as I know you do,\n\nBut you must join in souls to mock me too?\n\nIf you were men, as men you are in show,\n\nYou would not use a gentle lady so;\n\nTo vow, and swear, and superpraise my parts,\n\nWhen I am sure you hate me with your hearts.\n\nYou both are rivals, and love Hermia;\n\nAnd now both rivals, to mock Helena:\n\nA trim exploit, a manly enterprise,\n\nTo conjure tears up in a poor maids eyes\n\nWith your derision! none of noble sort\n\nWould so offend a virgin, and extort\n\nA poor souls patience, all to make you sport."
  },
  {
    "p": "A Midsummer nights dream",
    "l": "3.2.165",
    "s": "LYSANDER",
    "t": "You are unkind, Demetrius; be not so;\n\nFor you love Hermia; this you know I know:\n\nAnd here, with all good will, with all my heart,\n\nIn Hermias love I yield you up my part;\n\nAnd yours of Helena to me bequeath,\n\nWhom I do love and will do till my death."
  },
  {
    "p": "A Midsummer nights dream",
    "l": "3.2.171",
    "s": "HELENA",
    "t": "Never did mockers waste more idle breath."
  },
  {
    "p": "A Midsummer nights dream",
    "l": "3.2.172",
    "s": "DEMETRIUS",
    "t": "Lysander, keep thy Hermia; I will none:\n\nIf eer I loved her, all that love is gone.\n\nMy heart to her but as guest-wise sojournd,\n\nAnd now to Helen is it home returnd,\n\nThere to remain."
  },
  {
    "p": "A Midsummer nights dream",
    "l": "3.2.177",
    "s": "LYSANDER",
    "t": "Helen, it is not so."
  },
  {
    "p": "A Midsummer nights dream",
    "l": "3.2.178",
    "s": "DEMETRIUS",
    "t": "Disparage not the faith thou dost not know,\n\nLest, to thy peril, thou aby it dear.\n\nLook, where thy love comes; yonder is thy dear."
  },
  {
    "p": "A Midsummer nights dream",
    "l": "3.2.181",
    "s": "HERMIA",
    "t": "Dark night, that from the eye his function takes,\n\nThe ear more quick of apprehension makes;\n\nWherein it doth impair the seeing sense,\n\nIt pays the hearing double recompense.\n\nThou art not by mine eye, Lysander, found;\n\nMine ear, I thank it, brought me to thy sound\n\nBut why unkindly didst thou leave me so?"
  },
  {
    "p": "A Midsummer nights dream",
    "l": "3.2.188",
    "s": "LYSANDER",
    "t": "Why should he stay, whom love doth press to go?"
  },
  {
    "p": "A Midsummer nights dream",
    "l": "3.2.189",
    "s": "HERMIA",
    "t": "What love could press Lysander from my side?"
  },
  {
    "p": "A Midsummer nights dream",
    "l": "3.2.190",
    "s": "LYSANDER",
    "t": "Lysanders love, that would not let him bide,\n\nFair Helena, who more engilds the night\n\nThan all you fiery oes and eyes of light.\n\nWhy seekst thou me? could not this make thee know,\n\nThe hate I bear thee made me leave thee so?"
  },
  {
    "p": "A Midsummer nights dream",
    "l": "3.2.195",
    "s": "HERMIA",
    "t": "You speak not as you think: it cannot be."
  },
  {
    "p": "A Midsummer nights dream",
    "l": "3.2.196",
    "s": "HELENA",
    "t": "Lo, she is one of this confederacy!\n\nNow I perceive they have conjoind all three\n\nTo fashion this false sport, in spite of me.\n\nInjurious Hermia! most ungrateful maid!\n\nHave you conspired, have you with these contrived\n\nTo bait me with this foul derision?\n\nIs all the counsel that we two have shared,\n\nThe sisters vows, the hours that we have spent,\n\nWhen we have chid the hasty-footed time\n\nFor parting us,--O, is it all forgot?\n\nAll school-days friendship, childhood innocence?\n\nWe, Hermia, like two artificial gods,\n\nHave with our needles created both one flower,\n\nBoth on one sampler, sitting on one cushion,\n\nBoth warbling of one song, both in one key,\n\nAs if our hands, our sides, voices and minds,\n\nHad been incorporate. So we grow together,\n\nLike to a double cherry, seeming parted,\n\nBut yet an union in partition;\n\nTwo lovely berries moulded on one stem;\n\nSo, with two seeming bodies, but one heart;\n\nTwo of the first, like coats in heraldry,\n\nDue but to one and crowned with one crest.\n\nAnd will you rent our ancient love asunder,\n\nTo join with men in scorning your poor friend?\n\nIt is not friendly, tis not maidenly:\n\nOur sex, as well as I, may chide you for it,\n\nThough I alone do feel the injury."
  },
  {
    "p": "A Midsummer nights dream",
    "l": "3.2.224",
    "s": "HERMIA",
    "t": "I am amazed at your passionate words.\n\nI scorn you not: it seems that you scorn me."
  },
  {
    "p": "A Midsummer nights dream",
    "l": "3.2.226",
    "s": "HELENA",
    "t": "Have you not set Lysander, as in scorn,\n\nTo follow me and praise my eyes and face?\n\nAnd made your other love, Demetrius,\n\nWho even but now did spurn me with his foot,\n\nTo call me goddess, nymph, divine and rare,\n\nPrecious, celestial? Wherefore speaks he this\n\nTo her he hates? and wherefore doth Lysander\n\nDeny your love, so rich within his soul,\n\nAnd tender me, forsooth, affection,\n\nBut by your setting on, by your consent?\n\nWhat thought I be not so in grace as you,\n\nSo hung upon with love, so fortunate,\n\nBut miserable most, to love unloved?\n\nThis you should pity rather than despise."
  },
  {
    "p": "A Midsummer nights dream",
    "l": "3.2.240",
    "s": "HERNIA",
    "t": "I understand not what you mean by this."
  },
  {
    "p": "A Midsummer nights dream",
    "l": "3.2.241",
    "s": "HELENA",
    "t": "Ay, do, persever, counterfeit sad looks,\n\nMake mouths upon me when I turn my back;\n\nWink each at other; hold the sweet jest up:\n\nThis sport, well carried, shall be chronicled.\n\nIf you have any pity, grace, or manners,\n\nYou would not make me such an argument.\n\nBut fare ye well: tis partly my own fault;\n\nWhich death or absence soon shall remedy."
  },
  {
    "p": "A Midsummer nights dream",
    "l": "3.2.249",
    "s": "LYSANDER",
    "t": "Stay, gentle Helena; hear my excuse:\n\nMy love, my life my soul, fair Helena!"
  },
  {
    "p": "A Midsummer nights dream",
    "l": "3.2.251",
    "s": "HELENA",
    "t": "O excellent!"
  },
  {
    "p": "A Midsummer nights dream",
    "l": "3.2.252",
    "s": "HERMIA",
    "t": "Sweet, do not scorn her so."
  },
  {
    "p": "A Midsummer nights dream",
    "l": "3.2.253",
    "s": "DEMETRIUS",
    "t": "If she cannot entreat, I can compel."
  },
  {
    "p": "A Midsummer nights dream",
    "l": "3.2.254",
    "s": "LYSANDER",
    "t": "Thou canst compel no more than she entreat:\n\nThy threats have no more strength than her weak prayers.\n\nHelen, I love thee; by my life, I do:\n\nI swear by that which I will lose for thee,\n\nTo prove him false that says I love thee not."
  },
  {
    "p": "A Midsummer nights dream",
    "l": "3.2.259",
    "s": "DEMETRIUS",
    "t": "I say I love thee more than he can do."
  },
  {
    "p": "A Midsummer nights dream",
    "l": "3.2.260",
    "s": "LYSANDER",
    "t": "If thou say so, withdraw, and prove it too."
  },
  {
    "p": "A Midsummer nights dream",
    "l": "3.2.261",
    "s": "DEMETRIUS",
    "t": "Quick, come!"
  },
  {
    "p": "A Midsummer nights dream",
    "l": "3.2.262",
    "s": "HERMIA",
    "t": "Lysander, whereto tends all this?"
  },
  {
    "p": "A Midsummer nights dream",
    "l": "3.2.263",
    "s": "LYSANDER",
    "t": "Away, you Ethiope!"
  },
  {
    "p": "A Midsummer nights dream",
    "l": "3.2.264",
    "s": "DEMETRIUS",
    "t": "No, no; hell [        ]\n\nSeem to break loose; take on as you would follow,\n\nBut yet come not: you are a tame man, go!"
  },
  {
    "p": "A Midsummer nights dream",
    "l": "3.2.267",
    "s": "LYSANDER",
    "t": "Hang off, thou cat, thou burr! vile thing, let loose,\n\nOr I will shake thee from me like a serpent!"
  },
  {
    "p": "A Midsummer nights dream",
    "l": "3.2.269",
    "s": "HERMIA",
    "t": "Why are you grown so rude? what change is this?\n\nSweet love,--"
  },
  {
    "p": "A Midsummer nights dream",
    "l": "3.2.271",
    "s": "LYSANDER",
    "t": "Thy love! out, tawny Tartar, out!\n\nOut, loathed medicine! hated potion, hence!"
  },
  {
    "p": "A Midsummer nights dream",
    "l": "3.2.273",
    "s": "HERMIA",
    "t": "Do you not jest?"
  },
  {
    "p": "A Midsummer nights dream",
    "l": "3.2.274",
    "s": "HELENA",
    "t": "Yes, sooth; and so do you."
  },
  {
    "p": "A Midsummer nights dream",
    "l": "3.2.275",
    "s": "LYSANDER",
    "t": "Demetrius, I will keep my word with thee."
  },
  {
    "p": "A Midsummer nights dream",
    "l": "3.2.276",
    "s": "DEMETRIUS",
    "t": "I would I had your bond, for I perceive\n\nA weak bond holds you: Ill not trust your word."
  },
  {
    "p": "A Midsummer nights dream",
    "l": "3.2.278",
    "s": "LYSANDER",
    "t": "What, should I hurt her, strike her, kill her dead?\n\nAlthough I hate her, Ill not harm her so."
  },
  {
    "p": "A Midsummer nights dream",
    "l": "3.2.280",
    "s": "HERMIA",
    "t": "What, can you do me greater harm than hate?\n\nHate me! wherefore? O me! what news, my love!\n\nAm not I Hermia? are not you Lysander?\n\nI am as fair now as I was erewhile.\n\nSince night you loved me; yet since night you left\n\nme:\n\nWhy, then you left me--O, the gods forbid!--\n\nIn earnest, shall I say?"
  },
  {
    "p": "A Midsummer nights dream",
    "l": "3.2.288",
    "s": "LYSANDER",
    "t": "Ay, by my life;\n\nAnd never did desire to see thee more.\n\nTherefore be out of hope, of question, of doubt;\n\nBe certain, nothing truer; tis no jest\n\nThat I do hate thee and love Helena."
  },
  {
    "p": "A Midsummer nights dream",
    "l": "3.2.293",
    "s": "HERMIA",
    "t": "O me! you juggler! you canker-blossom!\n\nYou thief of love! what, have you come by night\n\nAnd stolen my loves heart from him?"
  },
  {
    "p": "A Midsummer nights dream",
    "l": "3.2.296",
    "s": "HELENA",
    "t": "Fine, ifaith!\n\nHave you no modesty, no maiden shame,\n\nNo touch of bashfulness? What, will you tear\n\nImpatient answers from my gentle tongue?\n\nFie, fie! you counterfeit, you puppet, you!"
  },
  {
    "p": "A Midsummer nights dream",
    "l": "3.2.301",
    "s": "HERMIA",
    "t": "Puppet? why so? ay, that way goes the game.\n\nNow I perceive that she hath made compare\n\nBetween our statures; she hath urged her height;\n\nAnd with her personage, her tall personage,\n\nHer height, forsooth, she hath prevaild with him.\n\nAnd are you grown so high in his esteem;\n\nBecause I am so dwarfish and so low?\n\nHow low am I, thou painted maypole? speak;\n\nHow low am I? I am not yet so low\n\nBut that my nails can reach unto thine eyes."
  },
  {
    "p": "A Midsummer nights dream",
    "l": "3.2.311",
    "s": "HELENA",
    "t": "I pray you, though you mock me, gentlemen,\n\nLet her not hurt me: I was never curst;\n\nI have no gift at all in shrewishness;\n\nI am a right maid for my cowardice:\n\nLet her not strike me. You perhaps may think,\n\nBecause she is something lower than myself,\n\nThat I can match her."
  },
  {
    "p": "A Midsummer nights dream",
    "l": "3.2.318",
    "s": "HERMIA",
    "t": "Lower! hark, again."
  },
  {
    "p": "A Midsummer nights dream",
    "l": "3.2.319",
    "s": "HELENA",
    "t": "Good Hermia, do not be so bitter with me.\n\nI evermore did love you, Hermia,\n\nDid ever keep your counsels, never wrongd you;\n\nSave that, in love unto Demetrius,\n\nI told him of your stealth unto this wood.\n\nHe followd you; for love I followd him;\n\nBut he hath chid me hence and threatend me\n\nTo strike me, spurn me, nay, to kill me too:\n\nAnd now, so you will let me quiet go,\n\nTo Athens will I bear my folly back\n\nAnd follow you no further: let me go:\n\nYou see how simple and how fond I am."
  },
  {
    "p": "A Midsummer nights dream",
    "l": "3.2.331",
    "s": "HERMIA",
    "t": "Why, get you gone: who ist that hinders you?"
  },
  {
    "p": "A Midsummer nights dream",
    "l": "3.2.332",
    "s": "HELENA",
    "t": "A foolish heart, that I leave here behind."
  },
  {
    "p": "A Midsummer nights dream",
    "l": "3.2.333",
    "s": "HERMIA",
    "t": "What, with Lysander?"
  },
  {
    "p": "A Midsummer nights dream",
    "l": "3.2.334",
    "s": "HELENA",
    "t": "With Demetrius."
  },
  {
    "p": "A Midsummer nights dream",
    "l": "3.2.335",
    "s": "LYSANDER",
    "t": "Be not afraid; she shall not harm thee, Helena."
  },
  {
    "p": "A Midsummer nights dream",
    "l": "3.2.336",
    "s": "DEMETRIUS",
    "t": "No, sir, she shall not, though you take her part."
  },
  {
    "p": "A Midsummer nights dream",
    "l": "3.2.337",
    "s": "HELENA",
    "t": "O, when shes angry, she is keen and shrewd!\n\nShe was a vixen when she went to school;\n\nAnd though she be but little, she is fierce."
  },
  {
    "p": "A Midsummer nights dream",
    "l": "3.2.340",
    "s": "HERMIA",
    "t": "Little again! nothing but low and little!\n\nWhy will you suffer her to flout me thus?\n\nLet me come to her."
  },
  {
    "p": "A Midsummer nights dream",
    "l": "3.2.343",
    "s": "LYSANDER",
    "t": "Get you gone, you dwarf;\n\nYou minimus, of hindering knot-grass made;\n\nYou bead, you acorn."
  },
  {
    "p": "A Midsummer nights dream",
    "l": "3.2.346",
    "s": "DEMETRIUS",
    "t": "You are too officious\n\nIn her behalf that scorns your services.\n\nLet her alone: speak not of Helena;\n\nTake not her part; for, if thou dost intend\n\nNever so little show of love to her,\n\nThou shalt aby it."
  },
  {
    "p": "A Midsummer nights dream",
    "l": "3.2.352",
    "s": "LYSANDER",
    "t": "Now she holds me not;\n\nNow follow, if thou darest, to try whose right,\n\nOf thine or mine, is most in Helena."
  },
  {
    "p": "A Midsummer nights dream",
    "l": "3.2.355",
    "s": "DEMETRIUS",
    "t": "Follow! nay, Ill go with thee, cheek by jole."
  },
  {
    "p": "A Midsummer nights dream",
    "l": "3.2.356",
    "s": "HERMIA",
    "t": "You, mistress, all this coil is long of you:\n\nNay, go not back."
  },
  {
    "p": "A Midsummer nights dream",
    "l": "3.2.358",
    "s": "HELENA",
    "t": "I will not trust you, I,\n\nNor longer stay in your curst company.\n\nYour hands than mine are quicker for a fray,\n\nMy legs are longer though, to run away."
  },
  {
    "p": "A Midsummer nights dream",
    "l": "3.2.362",
    "s": "HERMIA",
    "t": "I am amazed, and know not what to say."
  },
  {
    "p": "A Midsummer nights dream",
    "l": "3.2.363",
    "s": "OBERON",
    "t": "This is thy negligence: still thou mistakest,\n\nOr else committst thy knaveries wilfully."
  },
  {
    "p": "A Midsummer nights dream",
    "l": "3.2.365",
    "s": "PUCK",
    "t": "Believe me, king of shadows, I mistook.\n\nDid not you tell me I should know the man\n\nBy the Athenian garment be had on?\n\nAnd so far blameless proves my enterprise,\n\nThat I have nointed an Athenians eyes;\n\nAnd so far am I glad it so did sort\n\nAs this their jangling I esteem a sport."
  },
  {
    "p": "A Midsummer nights dream",
    "l": "3.2.372",
    "s": "OBERON",
    "t": "Thou seest these lovers seek a place to fight:\n\nHie therefore, Robin, overcast the night;\n\nThe starry welkin cover thou anon\n\nWith drooping fog as black as Acheron,\n\nAnd lead these testy rivals so astray\n\nAs one come not within anothers way.\n\nLike to Lysander sometime frame thy tongue,\n\nThen stir Demetrius up with bitter wrong;\n\nAnd sometime rail thou like Demetrius;\n\nAnd from each other look thou lead them thus,\n\nTill oer their brows death-counterfeiting sleep\n\nWith leaden legs and batty wings doth creep:\n\nThen crush this herb into Lysanders eye;\n\nWhose liquor hath this virtuous property,\n\nTo take from thence all error with his might,\n\nAnd make his eyeballs roll with wonted sight.\n\nWhen they next wake, all this derision\n\nShall seem a dream and fruitless vision,\n\nAnd back to Athens shall the lovers wend,\n\nWith league whose date till death shall never end.\n\nWhiles I in this affair do thee employ,\n\nIll to my queen and beg her Indian boy;\n\nAnd then I will her charmed eye release\n\nFrom monsters view, and all things shall be peace."
  },
  {
    "p": "A Midsummer nights dream",
    "l": "3.2.396",
    "s": "PUCK",
    "t": "My fairy lord, this must be done with haste,\n\nFor nights swift dragons cut the clouds full fast,\n\nAnd yonder shines Auroras harbinger;\n\nAt whose approach, ghosts, wandering here and there,\n\nTroop home to churchyards: damned spirits all,\n\nThat in crossways and floods have burial,\n\nAlready to their wormy beds are gone;\n\nFor fear lest day should look their shames upon,\n\nThey willfully themselves exile from light\n\nAnd must for aye consort with black-browd night."
  },
  {
    "p": "A Midsummer nights dream",
    "l": "3.2.406",
    "s": "OBERON",
    "t": "But we are spirits of another sort:\n\nI with the mornings love have oft made sport,\n\nAnd, like a forester, the groves may tread,\n\nEven till the eastern gate, all fiery-red,\n\nOpening on Neptune with fair blessed beams,\n\nTurns into yellow gold his salt green streams.\n\nBut, notwithstanding, haste; make no delay:\n\nWe may effect this business yet ere day."
  },
  {
    "p": "A Midsummer nights dream",
    "l": "3.2.414",
    "s": "PUCK",
    "t": "Up and down, up and down,\n\nI will lead them up and down:\n\nI am feard in field and town:\n\nGoblin, lead them up and down.\n\nHere comes one."
  },
  {
    "p": "A Midsummer nights dream",
    "l": "3.2.419",
    "s": "LYSANDER",
    "t": "Where art thou, proud Demetrius? speak thou now."
  },
  {
    "p": "A Midsummer nights dream",
    "l": "3.2.420",
    "s": "PUCK",
    "t": "Here, villain; drawn and ready. Where art thou?"
  },
  {
    "p": "A Midsummer nights dream",
    "l": "3.2.421",
    "s": "LYSANDER",
    "t": "I will be with thee straight."
  },
  {
    "p": "A Midsummer nights dream",
    "l": "3.2.422",
    "s": "PUCK",
    "t": "Follow me, then,\n\nTo plainer ground."
  },
  {
    "p": "A Midsummer nights dream",
    "l": "3.2.424",
    "s": "DEMETRIUS",
    "t": "Lysander! speak again:\n\nThou runaway, thou coward, art thou fled?\n\nSpeak! In some bush? Where dost thou hide thy head?"
  },
  {
    "p": "A Midsummer nights dream",
    "l": "3.2.427",
    "s": "PUCK",
    "t": "Thou coward, art thou bragging to the stars,\n\nTelling the bushes that thou lookst for wars,\n\nAnd wilt not come? Come, recreant; come, thou child;\n\nIll whip thee with a rod: he is defiled\n\nThat draws a sword on thee."
  },
  {
    "p": "A Midsummer nights dream",
    "l": "3.2.432",
    "s": "DEMETRIUS",
    "t": "Yea, art thou there?"
  },
  {
    "p": "A Midsummer nights dream",
    "l": "3.2.433",
    "s": "PUCK",
    "t": "Follow my voice: well try no manhood here."
  },
  {
    "p": "A Midsummer nights dream",
    "l": "3.2.434",
    "s": "LYSANDER",
    "t": "He goes before me and still dares me on:\n\nWhen I come where he calls, then he is gone.\n\nThe villain is much lighter-heeld than I:\n\nI followd fast, but faster he did fly;\n\nThat fallen am I in dark uneven way,\n\nAnd here will rest me.\n\nCome, thou gentle day!\n\nFor if but once thou show me thy grey light,\n\nIll find Demetrius and revenge this spite."
  },
  {
    "p": "A Midsummer nights dream",
    "l": "3.2.443",
    "s": "PUCK",
    "t": "Ho, ho, ho! Coward, why comest thou not?"
  },
  {
    "p": "A Midsummer nights dream",
    "l": "3.2.444",
    "s": "DEMETRIUS",
    "t": "Abide me, if thou darest; for well I wot\n\nThou runnst before me, shifting every place,\n\nAnd darest not stand, nor look me in the face.\n\nWhere art thou now?"
  },
  {
    "p": "A Midsummer nights dream",
    "l": "3.2.448",
    "s": "PUCK",
    "t": "Come hither: I am here."
  },
  {
    "p": "A Midsummer nights dream",
    "l": "3.2.449",
    "s": "DEMETRIUS",
    "t": "Nay, then, thou mockst me. Thou shalt buy this dear,\n\nIf ever I thy face by daylight see:\n\nNow, go thy way. Faintness constraineth me\n\nTo measure out my length on this cold bed.\n\nBy days approach look to be visited."
  },
  {
    "p": "A Midsummer nights dream",
    "l": "3.2.454",
    "s": "HELENA",
    "t": "O weary night, O long and tedious night,\n\nAbate thy hour! Shine comforts from the east,\n\nThat I may back to Athens by daylight,\n\nFrom these that my poor company detest:\n\nAnd sleep, that sometimes shuts up sorrows eye,\n\nSteal me awhile from mine own company."
  },
  {
    "p": "A Midsummer nights dream",
    "l": "3.2.460",
    "s": "PUCK",
    "t": "Yet but three? Come one more;\n\nTwo of both kinds make up four.\n\nHere she comes, curst and sad:\n\nCupid is a knavish lad,\n\nThus to make poor females mad."
  },
  {
    "p": "A Midsummer nights dream",
    "l": "3.2.465",
    "s": "HERMIA",
    "t": "Never so weary, never so in woe,\n\nBedabbled with the dew and torn with briers,\n\nI can no further crawl, no further go;\n\nMy legs can keep no pace with my desires.\n\nHere will I rest me till the break of day.\n\nHeavens shield Lysander, if they mean a fray!"
  }
]